CalculoNumerosPrimos/__init__.py
CalculoNumerosPrimos-1.0.dist-info/LICENSE
CalculoNumerosPrimos-1.0.dist-info/METADATA
CalculoNumerosPrimos-1.0.dist-info/WHEEL
CalculoNumerosPrimos-1.0.dist-info/top_level.txt
CalculoNumerosPrimos-1.0.dist-info/RECORD
